rashi/__init__.py
rashi/main.py
rashi-0.1.1.dist-info/LICENSE
rashi-0.1.1.dist-info/METADATA
rashi-0.1.1.dist-info/WHEEL
rashi-0.1.1.dist-info/top_level.txt
rashi-0.1.1.dist-info/RECORD
