Metadata-Version: 2.1
Name: rashi
Version: 0.1.1
Summary: Get Rashi
Home-page: https://github.com/Crian69/rashi
Author: Crain69 (Chirayu Prasai)
Author-email: <chirayuprasai11@gmail.com>
License: UNKNOWN
Keywords: python,nepali,rashi,hamro,patro,horoscope
Platform: UNKNOWN
Classifier: Development Status :: 5 - Production/Stable
Classifier: Intended Audience :: Developers
Classifier: Programming Language :: Python :: 3
Classifier: Operating System :: Unix
Classifier: Operating System :: Microsoft :: Windows
Requires-Dist: beautifulsoup4
Requires-Dist: requests
